[
	{
		"enabled": true,
		"updateUrl": null,
		"md5Url": null,
		"url": null,
		"originalMd5": null,
		"installDate": 1585849037271,
		"name": "learningsuite.byu.edu",
		"sections": [
			{
				"code": "body {\n    background-color: #222222;\n    box-shadow: none;\n}\n\nhtml {\n    background: #222222;\n}\n\n.allCourses {\n    -webkit-box-shadow: none;\n    -moz-box-shadow: none;\n    box-shadow: none;\n}\n\n#tab-course a.current {\n    background-color: #444444;\n    border: none;\n    color: #f5f5f5;\n}\n\n#tab-course a {\n    text-shadow: none;\n}\n\n#sidenav h2 {\n    color: #f5f5f5;\n}\n\n#sidenav {\n    background: transparent;\n    color: #f5f5f5;\n    background-color: #444444;\n    height: 100%;\n}\n\n#sidenav a {\n    color: #f5f5f5;\n    background-color: #444444;\n}\n\n#sidenav a.current {\n    background: transparent;\n    color: #f5f5f5;\n    background-color: #444444;\n    border: none;\n}\n\nbody > footer {\n    background: #333333;\n    border: none;\n}\n\n.course a.course-title {\n    color: #58B\n}\n\na,\na:link {\n    color: #58B;\n}\n\n.btn-primary,\na.action2,\na.edit,\ndiv.addDayButton {\n    text-shadow: none;\n    color: #f5f5f5;\n    background-color: #36A;\n    background-image: none;\n}\n\n.btn,\n.basic_button,\na.action,\ninput.action,\na.action2,\na.edit a.edit2,\n#sidenav a.edit,\ndiv.addDayButton,\na.cancel,\na.cancelPopup {\n    text-shadow: none;\n    background-image: none;\n    background-color: #D5D5D5;\n}\n\n#main {\n    color: #f5f5f5;\n}\n\n.dashboardItem .greenHeader {\n    border-bottom: none;\n}\n\n.greenHeader {\n    background: none;\n    background-color: transparent !important;\n    background-image: none;\n    color: #f5f5f5;\n}\n\n.greenbar {\n    background: none;\n    background-color: #444444;\n    background-image: none;\n    color: #f5f5f5;\n}\n\n.dashboardDay .categoryTitle {\n    color: #f5f5f5;\n    background: none;\n    background-color: transparent;\n}\n\n#dashboardAnnounce h2,\n#dashboardAnnounce p {\n    color: #f5f5f5;\n}\n\nh2#scheduleTitle {\n    color: #58B;\n}\n\n.desc h2 {\n    color: #58B;\n}\n\nnav#sidenav a:hover {\n    color: #222222;\n    background-color: #888;\n    border: none !important;\n}\n\nh1#page-title {\n    color: #58B;\n}\n\ndiv#page-content.content-page-body p {\n    color: #f5f5f5 !important;\n}\n\ndiv#page-content.content-page-body a {\n    color: #58B !important;\n    text-decoration: none;\n    background-color: transparent;\n    background: none;\n}\n\n#assignmentsTable .category {\n    background: none;\n    background-image: none;\n    background-color: #666 !important;\n    border-bottom: 2px solid #AAA;\n}\n\n#assignmentsTable th span,\n#assignmentsTable th.percent-col,\n#assignmentsTable th.stats-col {\n    color: #f5f5f5;\n}\n\ntbody tr.assignment td.title-col a.viewPrintLink {\n    color: #69C;\n    font-weight: 500;\n}\n\n.view-stats.btn.btn-primary.btn-small {\n    color: #3A3A3A;\n    background-color: #69C;\n}\n\n.view-stats.btn.btn-primary.btn-small:hover {\n    color: #BBB;\n    background-color: #24A;\n}\n\n.submitAssignmentLink.btn.btn-success.btn-small {\n    color: #3A3A3A;\n}\n\n.submitAssignmentLink.btn.btn-success.btn-small:hover {\n    color: #D3D3D3;\n}\n\n.collapse-col {\n    color: #236;\n    font-weight: 700;\n}\n\n#assignmentsFooter #calculationOptions {\n    color: #f5f5f5;\n    background: none;\n    background-image: none;\n    background-color: #444;\n}\n\n#assignmentsFooter .course-header {\n    color: #f5f5f5;\n    background-color: #444;\n}\n\n#assignmentsFooter #totalScoreContainer #totalScoreInfo {\n    color: #d5d5d5;\n}\n\n#assignmentsFooter #totalScoreContainer .score-header {\n    color: #d5d5d5;\n}\n\n#assignmentsFooter #totalScoreContainer .weightedCategoryWarning {\n    color: #d5d5d5;\n}\n\n#assignmentsFooter #currentScoreContainer #currentScoreInfo {\n    color: #d5d5d5;\n}\n\n.scheduleWeek {\n    background: none;\n    background-image: none;\n    background-color: #777;\n}\n\n.scheduleWeek .week-label {\n    color: #258;\n}\n\nh3#instructorInfo.section_heading_minor {\n    color: #58B;\n}\n\nh1.section_heading_major.syllabus_heading {\n    color: #58B;\n}\n\n#calendarTable tbody p {\n    color: #f5f5f5;\n}\n\n#calendarTable tbody .calendarItem .clickForDesc {\n    color: #58B;\n}\n\n#calendarViewTitle #timePeriod {\n    color: #f5f5f5;\n}\n\n#gridView tr .class-day-cell,\n.sidebar td {\n    background-color: #333;\n}\n\nheader#aggregateCalendarHeader {\n    background-color: #222 !important;\n}\n\nheader#aggregateCalendarHeader .dateNav h2.date {\n    color: #58B;\n}\n\ndiv.sidebarCalendar {\n    color: #444;\n}\n\n.dashboardAnnouncement .dashboardAnnouncementText span {\n    color: #f5f5f5 !important;\n    background-color: transparent !important;\n}\n\n.dashboardAnnouncement h3 {\n    color: #58B;\n}\n\n.course-refresh.btn.btn-small {\n    background-color: #08b3da !important;\n    border: none;\n    color: #f5f5f5;\n    padding: 5px 16px !important;\n}\n\n.course-refresh.btn.btn-small:hover {\n    background-color: #58B !important;\n}\n\n#sidenav a.current {\n    color: #69F;\n}\n\na.btn.btn-link.renderMessageSettings {\n    background-color: transparent;\n    background: none;\n    background-image: none;\n}\n\n.announcement .announcementContent .announcementText p span {\n    color: #f5f5f5 !important;\n    background-color: transparent !important;\n}\n\n.announcement .announcementContent .announcementText p a {\n    color: #f5f5f5 !important;\n    background-color: transparent !important;\n}\n\n/*\nMESSAGES SECTION\n*/\n#messagesFullScreenPopup #conversationView header,\n#messagesFullScreenPopup #conversationListView header {\n    color: #E5E5E5;\n    background-color: #222;\n}\n\n#messagesFullScreenPopup #conversationView header .conversationInfo {\n    color: #f5f5f5;\n}\n\n#messagesFullScreenPopup #conversationListView header .searchWrapper,\n#messagesFullScreenPopup #conversationListview header .searchWrapper input {\n    background-color: #444;\n    border: none;\n}\n\n#messagesFullScreenPopup #conversationListView #conversationList li .selectConversation.underlay {\n    color: #f5f5f5;\n    background-color: #333;\n}\n\n#messagesFullScreenPopup #conversationListView #conversationList li .selectConversation {\n    color: #d5d5d5;\n}\n\n#messagesFullScreenPopup #conversationListView #conversationList li .conversationRecipients {\n    color: #b1cdff;\n}\n\n#messagesFullScreenPopup #conversationListView #conversationList li .courseIndicator {\n    color: #fff;\n}\n\nul#messageList {\n    background-color: #555 !important;\n    background: none !important;\n    background-image: none !important;\n}\n\nli.message {\n    background-color: #5a5a5a !important;\n    color: #fff;\n}\n\n#messagesFullScreenPopup #conversationView #messageList .message .senderName {\n    color: #bce;\n}\n\n#messagesFullScreenPopup #conversationView .conversationWrapper {\n    background-color: #111;\n}\n\n#messagesFullScreenPopup #conversationView #replyInterface {\n    color: #fff;\n    background-color: #444;\n}\n\n#messagesFullScreenPopup #conversationView #replyInterface .btn {\n    border: none;\n    color: #fff;\n    background-color: #666;\n}\n\n/*\nSETTINGS POPUP\n*/\n#preferencesPopup {\n    background-color: #222 !important;\n}\n\n#preferencesPopup .tabContent {\n    background-color: #333 !important;\n    border: none !important;\n}\n\n#preferencesPopup .nav-tabs > .active > a {\n    background-color: #333 !important;\n}\n\n#preferencesPopup .nav-tabs a {\n    color: #f5f5f5;\n}\n\n#preferencesPopup .btn {\n    background-color: #444;\n    border: none;\n    color: #f5f5f5;\n}\n\n#preferencesPopup #messagePreferences #messageTabNav .messageTab {\n    color: #f5f5f5;\n}\n\n#preferencesPopup #messagePreferences #messageTabNav .messageTab:hover {\n    background-color: #666;\n}\n\n#preferencesPopup #messagePreferences #filterContent h3 {\n    color: #58B !important;\n}",
				"domains": [
					"learningsuite.byu.edu"
				]
			}
		],
		"updateDate": 1585869911443,
		"_id": "c16cf1d8-d518-43bd-acc3-f036296a9583",
		"_rev": 1585869911443,
		"id": 10
	}
]
